hello.py
basic_ida_plugin-0.1.0.dist-info/METADATA
basic_ida_plugin-0.1.0.dist-info/WHEEL
basic_ida_plugin-0.1.0.dist-info/entry_points.txt
basic_ida_plugin-0.1.0.dist-info/top_level.txt
basic_ida_plugin-0.1.0.dist-info/RECORD
